{
    "name":  "ODEM",
    "website":  "https://odem.io",
    "description":  "ODEM, short for \u0027On-Demand Education Marketplace\u0027, is a blockchain-based distributed network that allows university students to interact with their professors and academic partners without intermediaries.",
    "explorer":  "https://etherscan.io/token/0xbf52F2ab39e26E0951d2a02b49B7702aBe30406a",
    "symbol":  "ODEM",
    "decimals":  18,
    "status":  "active",
    "logoURL":  "assets/blockchains/1/contracts/0XBF52F2AB39E26E0951D2A02B49B7702ABE30406A/logo.png",
    "id":  "0xbf52F2ab39e26E0951d2a02b49B7702aBe30406a"
}