{
    "name":  "Flooring Lab Credit",
    "website":  "https://flooring.io/",
    "description":  "The $FLC token is the native currency that powers the Flooring Protocol ecosystem. It unlocks and fuels customized platform utilities for all users.",
    "explorer":  "https://etherscan.io/token/0x102c776ddb30c754ded4fdcc77a19230a60d4e4f",
    "symbol":  "FLC",
    "decimals":  18,
    "status":  "active",
    "logoURL":  "assets/blockchains/1/contracts/0X102C776DDB30C754DED4FDCC77A19230A60D4E4F/logo.png",
    "id":  "0x102c776DDB30C754dEd4fDcC77A19230A60D4e4f",
    "links":  [
                  {
                      "name":  "x",
                      "url":  "https://x.com/flooringproto"
                  }
              ]
}