{
  "name": "GoChain",
  "symbol": "GO",
  "decimals": 18,
  "website": "https://gochain.io",
  "description": "GoChain is a scalable, smart contract blockchain that is fast, secure and green. It enables developers to lift and shift from Ethereum to GoChain for 100x increased performance. ",
  "explorer": "https://explorer.gochain.io/home",
  "links": [
    {
      "name": "github",
      "url": "https://github.com/gochain"
    },
    {
      "name": "x",
      "url": "https://x.com/go_chain"
    },
    {
      "name": "reddit",
      "url": "https://reddit.com/r/OfficialGoChain"
    },
    {
      "name": "whitepaper",
      "url": "https://gochain.foundation/gochain-whitepaper-v2.1.2.pdf"
    }
  ],
  "research": "https://research.binance.com/en/projects/gochain"
}
